moniker/__init__.py
moniker/__main__.py
moniker/__version__.py
moniker/moniker.py
moniker/tests/__init__.py
moniker/tests/test_main.py
moniker-0.0.1.dist-info/DESCRIPTION.rst
moniker-0.0.1.dist-info/entry_points.txt
moniker-0.0.1.dist-info/METADATA
moniker-0.0.1.dist-info/metadata.json
moniker-0.0.1.dist-info/RECORD
moniker-0.0.1.dist-info/top_level.txt
moniker-0.0.1.dist-info/WHEEL
