Metadata-Version: 2.0
Name: moniker
Version: 0.0.1
Summary: Simple batch file renaming tool.
Home-page: https://github.com/jjangsangy/moniker.git
Author: Sang Han
Author-email: jjangsangy@gmail.com
License: Apache License 2.0
Download-URL: https://github.com/jjangsangy/moniker.git
Platform: UNKNOWN
Classifier: Development Status :: 5 - Production/Stable
Classifier: Environment :: Console
Classifier: Intended Audience :: Developers
Classifier: Natural Language :: English
Classifier: License :: OSI Approved :: Apache Software License
Classifier: Operating System :: OS Independent
Classifier: Programming Language :: Unix Shell
Classifier: Programming Language :: Python
Classifier: Programming Language :: Python :: 2.7
Classifier: Programming Language :: Python :: 3.3
Classifier: Programming Language :: Python :: 3.4
Classifier: Topic :: Software Development :: Libraries :: Python Modules
Classifier: Topic :: Utilities
